setup.py
matrix_fdrx/__init__.py
matrix_fdrx/matrix.py
matrix_fdrx.egg-info/PKG-INFO
matrix_fdrx.egg-info/SOURCES.txt
matrix_fdrx.egg-info/dependency_links.txt
matrix_fdrx.egg-info/not-zip-safe
matrix_fdrx.egg-info/top_level.txt