Metadata-Version: 1.0
Name: matrix-fdrx
Version: 0.0.1
Summary: test package - do not use
Home-page: UNKNOWN
Author: Cause It's Fun Jan
Author-email: UNKNOWN
License: UNKNOWN
Platform: UNKNOWN
